gostrat/__init__.py
gostrat/gostrat.py
gostrat/graph.py
gostrat/version.py
gostrat-0.0.8.dist-info/DESCRIPTION.rst
gostrat-0.0.8.dist-info/METADATA
gostrat-0.0.8.dist-info/RECORD
gostrat-0.0.8.dist-info/WHEEL
gostrat-0.0.8.dist-info/entry_points.txt
gostrat-0.0.8.dist-info/metadata.json
gostrat-0.0.8.dist-info/top_level.txt
