Metadata-Version: 2.0
Name: gostrat
Version: 0.0.8
Summary: Tool to stratify GO terms based on first significant parent
Home-page: https://bitbucket.org/bucab/gostrat
Author: Adam Labadorf and the BU CAB Team
Author-email: labadorf@bu.edu
License: MIT
Keywords: bioinformatics,biology,sequencing,NGS
Platform: UNKNOWN
Classifier: Development Status :: 3 - Alpha
Classifier: Intended Audience :: Science/Research
Classifier: Environment :: Console
Classifier: License :: OSI Approved :: MIT License
Classifier: Programming Language :: Python :: 3
Classifier: Topic :: Scientific/Engineering :: Bio-Informatics
Requires-Python: ~=3.3
Requires-Dist: de-toolkit
Requires-Dist: docopt
Requires-Dist: future
Requires-Dist: goatools
Requires-Dist: matplotlib
Requires-Dist: mygene
Requires-Dist: networkx
Requires-Dist: pandas
Requires-Dist: pyyaml
Requires-Dist: setuptools
